{
  "enabled": true,
  "alarms": [
    {
      "alarm_id": "alarm_20260603180400",
      "name": "盘前持仓与市场检查",
      "enabled": true,
      "trigger_time": "09:10",
      "weekdays": [
        1,
        2,
        3,
        4,
        5
      ],
      "task": "盘前检查：1.持仓三花智控002050(成本46.08/止损40/止盈52)最新行情和止损位是否安全；2.三花智控若冲高50-52元出现放量滞涨考虑减仓锁利，跌破45元趋势支撑需警惕；3.候选池太极实业600667(目标14-15元低吸)和火炬电子603678(目标58-60元低吸)是否回调至买入区间；4.市场整体情绪和板块走势判断；5.根据检查结果决定是否需要执行交易动作。",
      "run_once": false
    },
    {
      "alarm_id": "alarm_20260603180417",
      "name": "盘中持仓监控",
      "enabled": true,
      "trigger_time": "10:30",
      "weekdays": [
        1,
        2,
        3,
        4,
        5
      ],
      "task": "盘中监控：1.三花智控002050(成本46.08/止损40/止盈52)若冲高50-52元出现放量滞涨考虑减仓锁利，跌破45元趋势支撑需警惕；2.若触发止损或止盈条件，用mx-data验证A股实时价格后执行相应操作；3.候选池太极实业600667和火炬电子603678是否回调至买入区间；4.关注持仓浮盈变化和市场情绪。",
      "run_once": false
    },
    {
      "alarm_id": "alarm_20260605180309",
      "name": "午后持仓与候选复查",
      "enabled": true,
      "trigger_time": "13:05",
      "weekdays": [
        1,
        2,
        3,
        4,
        5
      ],
      "task": "午后复查：1.三花智控002050(成本46.08/止损40/止盈52)午后走势，若冲高50-52元放量滞涨考虑减仓锁利，跌破45元趋势支撑需警惕；2.候选池太极实业600667(目标14-15元)和火炬电子603678(目标58-60元)是否回调至买入区间；3.下午盘市场情绪变化对持仓影响；4.若为周五尾盘需评估周末风险是否需要减仓。",
      "run_once": false
    },
    {
      "alarm_id": "alarm_20260605180316",
      "name": "尾盘风险复查",
      "enabled": true,
      "trigger_time": "14:30",
      "weekdays": [
        1,
        2,
        3,
        4,
        5
      ],
      "task": "尾盘复查：1.三花智控002050尾盘走势，若冲高放量滞涨或冲高回落考虑减仓锁利，跌破45元趋势支撑需警惕；2.候选池太极实业600667和火炬电子603678是否回调至买入区间可尾盘低吸；3.评估隔夜/周末风险是否需要减仓保护；4.若为周五需特别评估周末持仓风险；5.根据复查结果决定是否执行交易动作。",
      "run_once": false
    }
  ]
}
